q2_brocc/__init__.py
q2_brocc/_version.py
q2_brocc/citations.bib
q2_brocc/plugin_setup.py
q2_brocc/tests/__init__.py
q2_brocc/tests/test_brocc_assignment.py
q2_brocc/tests/data/query.fasta
q2_brocc/tests/data/somefungi.fasta
q2_brocc/tests/data/somefungi.fasta.nhr
q2_brocc/tests/data/somefungi.fasta.nin
q2_brocc/tests/data/somefungi.fasta.nsq
q2_brocc-2018.6.0.dev0.dist-info/METADATA
q2_brocc-2018.6.0.dev0.dist-info/RECORD
q2_brocc-2018.6.0.dev0.dist-info/WHEEL
q2_brocc-2018.6.0.dev0.dist-info/entry_points.txt
q2_brocc-2018.6.0.dev0.dist-info/top_level.txt
